pangeamt_release_test/__init__.py
pangeamt_release_test/foo.py
pangeamt_release_test-1.0.0.dist-info/METADATA
pangeamt_release_test-1.0.0.dist-info/WHEEL
pangeamt_release_test-1.0.0.dist-info/top_level.txt
pangeamt_release_test-1.0.0.dist-info/RECORD
