Metadata-Version: 2.1
Name: pangeamt-release-test
Version: 1.0.0
Summary: release_test
Home-page: UNKNOWN
Author: Pangeamt
License: UNKNOWN
Platform: UNKNOWN
